CHANGELOG.rst
MANIFEST.in
README.md
setup.cfg
setup.py
C3.egg-info/PKG-INFO
C3.egg-info/SOURCES.txt
C3.egg-info/dependency_links.txt
C3.egg-info/not-zip-safe
C3.egg-info/requires.txt
C3.egg-info/top_level.txt
c3/__init__.py
c3/aws/__init__.py
c3/aws/ec2/__init__.py
c3/aws/ec2/ebs.py
c3/aws/ec2/elb.py
c3/aws/ec2/instances.py
c3/aws/ec2/security_groups.py
c3/utils/__init__.py
c3/utils/accounts.py
c3/utils/config.py
c3/utils/graphite.py
c3/utils/logging.py
c3/utils/naming.py
c3/utils/tagger.py
c3/utils/jgp/__init__.py
c3/utils/jgp/gen_entry.py
c3/utils/jgp/statement.py
scripts/C3EC2Provision.py