Metadata-Version: 1.1
Name: C3
Version: 0.1
Summary: CloudCloudCloud
Home-page: UNKNOWN
Author: Jesse Escobedo
Author-email: jesse.escobedo@citygridmedia.com
License: Apache
Keywords: C3 AWS automation cgm cloud devops
Platform: UNKNOWN
Classifier: Programming Language :: Python
Classifier: Programming Language :: Python :: 2.6
Classifier: Programming Language :: Python :: 2.7
Classifier: Intended Audience :: System Administrators 
